{
  "meta": {
    "strategy": "swing_allocator_btc_usdt",
    "symbol": "BTC-USDT",
    "timeframe": "1H",
    "from_date": "2018-01-01",
    "to_date": "2026-01-01",
    "cost_mode": "realistic",
    "config_overrides": {
      "use_mvrv": true,
      "use_rsi": false,
      "use_pi_cycle": true,
      "use_vix": false,
      "use_macd_4h": false
    },
    "generated_at": "2026-06-30T13:21:12.272719+00:00"
  },
  "statistics": {
    "total_rebalances": 129,
    "buy_count": 61,
    "sell_count": 68,
    "avg_btc_pct": 69.4,
    "min_btc_pct": 30.0,
    "max_btc_pct": 90.0,
    "initial_balance_usdt": 10000.0,
    "final_balance_usdt": 103019.08,
    "pnl_pct": 930.19,
    "final_btc_qty": 0.332405,
    "bnh_initial_btc": 0.731608,
    "btc_vs_bnh_ratio": 0.4543,
    "signal_frequency": {
      "regime_bull": 68,
      "halving_bear": 30,
      "mvrv_2.96": 1,
      "mvrv_2.53": 1,
      "regime_bear": 17,
      "halving_post": 20,
      "halving_bull": 42,
      "mvrv_2.52": 3,
      "mvrv_2.64": 2,
      "mvrv_2.70": 1,
      "mvrv_3.55": 1,
      "mvrv_2.57": 1,
      "mvrv_2.58": 1,
      "mvrv_2.61": 1
    }
  },
  "rebalances": [
    {
      "num": 1,
      "timestamp": "2018-01-01T00:00:00+00:00",
      "direction": "INIT",
      "price": 13668.52,
      "qty": 0.438964,
      "btc_pct_before": 0.0,
      "btc_pct_target": 0.6,
      "btc_pct_after": 0.6,
      "portfolio_usdt": 10000.0,
      "signals": [
        "init"
      ]
    },
    {
      "num": 2,
      "timestamp": "2018-01-01T01:00:00+00:00",
      "direction": "BUY",
      "price": 13355.0,
      "qty": 0.077498,
      "btc_pct_before": 0.595,
      "btc_pct_target": 0.7,
      "btc_pct_after": 0.7001,
      "portfolio_usdt": 9853.37,
      "signals": [
        "regime_bull",
        "halving_bear_onset"
      ]
    },
    {
      "num": 3,
      "timestamp": "2018-01-04T01:00:00+00:00",
      "direction": "SELL",
      "price": 15350.06,
      "qty": 0.091101,
      "btc_pct_before": 0.7285,
      "btc_pct_target": 0.6,
      "btc_pct_after": 0.6001,
      "portfolio_usdt": 10882.19,
      "signals": [
        "regime_bull",
        "halving_bear_onset",
        "mvrv_2.96"
      ]
    },
    {
      "num": 4,
      "timestamp": "2018-01-12T01:00:00+00:00",
      "direction": "BUY",
      "price": 13461.9,
      "qty": 0.098626,
      "btc_pct_before": 0.5682,
      "btc_pct_target": 0.7,
      "btc_pct_after": 0.7001,
      "portfolio_usdt": 10076.95,
      "signals": [
        "regime_bull",
        "halving_bear_onset"
      ]
    },
    {
      "num": 5,
      "timestamp": "2018-01-15T01:00:00+00:00",
      "direction": "SELL",
      "price": 13471.1,
      "qty": 0.075035,
      "btc_pct_before": 0.7003,
      "btc_pct_target": 0.6,
      "btc_pct_after": 0.6001,
      "portfolio_usdt": 10079.78,
      "signals": [
        "regime_bull",
        "halving_bear_onset",
        "mvrv_2.53"
      ]
    },
    {
      "num": 6,
      "timestamp": "2018-01-18T01:00:00+00:00",
      "direction": "BUY",
      "price": 11389.0,
      "qty": 0.113033,
      "btc_pct_before": 0.5592,
      "btc_pct_target": 0.7,
      "btc_pct_after": 0.7001,
      "portfolio_usdt": 9143.5,
      "signals": [
        "regime_bull",
        "halving_bear_onset"
      ]
    },
    {
      "num": 7,
      "timestamp": "2018-02-02T01:00:00+00:00",
      "direction": "SELL",
      "price": 8798.2,
      "qty": 0.125215,
      "btc_pct_before": 0.6433,
      "btc_pct_target": 0.5,
      "btc_pct_after": 0.5001,
      "portfolio_usdt": 7685.58,
      "signals": [
        "halving_bear_onset"
      ]
    },
    {
      "num": 8,
      "timestamp": "2018-02-14T13:00:00+00:00",
      "direction": "BUY",
      "price": 9187.8,
      "qty": 0.161617,
      "btc_pct_before": 0.5109,
      "btc_pct_target": 0.7,
      "btc_pct_after": 0.7002,
      "portfolio_usdt": 7854.09,
      "signals": [
        "regime_bull",
        "halving_bear_onset"
      ]
    },
    {
      "num": 9,
      "timestamp": "2018-03-01T01:00:00+00:00",
      "direction": "SELL",
      "price": 10390.4,
      "qty": 0.185915,
      "btc_pct_before": 0.7254,
      "btc_pct_target": 0.5,
      "btc_pct_after": 0.5002,
      "portfolio_usdt": 8571.48,
      "signals": [
        "halving_bear_onset"
      ]
    },
    {
      "num": 10,
      "timestamp": "2018-03-04T01:00:00+00:00",
      "direction": "BUY",
      "price": 11403.9,
      "qty": 0.139149,
      "btc_pct_before": 0.5234,
      "btc_pct_target": 0.7,
      "btc_pct_after": 0.7002,
      "portfolio_usdt": 8986.62,
      "signals": [
        "regime_bull",
        "halving_bear_onset"
      ]
    },
    {
      "num": 11,
      "timestamp": "2018-03-07T01:00:00+00:00",
      "direction": "SELL",
      "price": 10852.0,
      "qty": 0.151703,
      "btc_pct_before": 0.6897,
      "btc_pct_target": 0.5,
      "btc_pct_after": 0.5001,
      "portfolio_usdt": 8679.8,
      "signals": [
        "halving_bear_onset"
      ]
    },
    {
      "num": 12,
      "timestamp": "2018-03-10T01:00:00+00:00",
      "direction": "BUY",
      "price": 9279.4,
      "qty": 0.207222,
      "btc_pct_before": 0.4611,
      "btc_pct_target": 0.7,
      "btc_pct_after": 0.7003,
      "portfolio_usdt": 8048.42,
      "signals": [
        "regime_bull",
        "halving_bear_onset"
      ]
    },
    {
      "num": 13,
      "timestamp": "2018-03-13T01:00:00+00:00",
      "direction": "SELL",
      "price": 9092.1,
      "qty": 0.170946,
      "btc_pct_before": 0.696,
      "btc_pct_target": 0.5,
      "btc_pct_after": 0.5001,
      "portfolio_usdt": 7931.82,
      "signals": [
        "halving_bear_onset"
      ]
    },
    {
      "num": 14,
      "timestamp": "2018-03-31T01:00:00+00:00",
      "direction": "SELL",
      "price": 7085.8,
      "qty": 0.137525,
      "btc_pct_before": 0.4381,
      "btc_pct_target": 0.3,
      "btc_pct_after": 0.3001,
      "portfolio_usdt": 7054.35,
      "signals": [
        "regime_bear",
        "halving_bear_onset"
      ]
    },
    {
      "num": 15,
      "timestamp": "2018-11-24T21:00:00+00:00",
      "direction": "BUY",
      "price": 4013.5,
      "qty": 0.15993,
      "btc_pct_before": 0.1954,
      "btc_pct_target": 0.3,
      "btc_pct_after": 0.3,
      "portfolio_usdt": 6135.29,
      "signals": [
        "regime_bear",
        "halving_bear_onset"
      ]
    },
    {
      "num": 16,
      "timestamp": "2018-12-26T01:00:00+00:00",
      "direction": "BUY",
      "price": 3802.1,
      "qty": 0.176563,
      "btc_pct_before": 0.2888,
      "btc_pct_target": 0.4,
      "btc_pct_after": 0.4001,
      "portfolio_usdt": 6037.38,
      "signals": [
        "regime_bear"
      ]
    },
    {
      "num": 17,
      "timestamp": "2019-04-22T01:00:00+00:00",
      "direction": "BUY",
      "price": 5229.6,
      "qty": 0.426956,
      "btc_pct_before": 0.4784,
      "btc_pct_target": 0.8,
      "btc_pct_after": 0.8004,
      "portfolio_usdt": 6943.07,
      "signals": [
        "regime_bull"
      ]
    },
    {
      "num": 18,
      "timestamp": "2019-06-26T01:00:00+00:00",
      "direction": "SELL",
      "price": 11930.0,
      "qty": 0.11953,
      "btc_pct_before": 0.9014,
      "btc_pct_target": 0.8,
      "btc_pct_after": 0.8001,
      "portfolio_usdt": 14056.33,
      "signals": [
        "regime_bull"
      ]
    },
    {
      "num": 19,
      "timestamp": "2019-08-01T01:00:00+00:00",
      "direction": "SELL",
      "price": 10020.1,
      "qty": 0.208825,
      "btc_pct_before": 0.7708,
      "btc_pct_target": 0.6,
      "btc_pct_after": 0.6002,
      "portfolio_usdt": 12253.95,
      "signals": []
    },
    {
      "num": 20,
      "timestamp": "2019-08-05T01:00:00+00:00",
      "direction": "BUY",
      "price": 11411.8,
      "qty": 0.196641,
      "btc_pct_before": 0.6309,
      "btc_pct_target": 0.8,
      "btc_pct_after": 0.8002,
      "portfolio_usdt": 13271.99,
      "signals": [
        "regime_bull"
      ]
    },
    {
      "num": 21,
      "timestamp": "2019-09-08T01:00:00+00:00",
      "direction": "SELL",
      "price": 10483.1,
      "qty": 0.220429,
      "btc_pct_before": 0.7863,
      "btc_pct_target": 0.6,
      "btc_pct_after": 0.6002,
      "portfolio_usdt": 12404.55,
      "signals": []
    },
    {
      "num": 22,
      "timestamp": "2019-09-20T01:00:00+00:00",
      "direction": "BUY",
      "price": 10199.7,
      "qty": 0.246906,
      "btc_pct_before": 0.5936,
      "btc_pct_target": 0.8,
      "btc_pct_after": 0.8002,
      "portfolio_usdt": 12199.88,
      "signals": [
        "regime_bull"
      ]
    },
    {
      "num": 23,
      "timestamp": "2019-09-25T05:00:00+00:00",
      "direction": "SELL",
      "price": 8495.6,
      "qty": 0.210695,
      "btc_pct_before": 0.7694,
      "btc_pct_target": 0.6,
      "btc_pct_after": 0.6002,
      "portfolio_usdt": 10565.48,
      "signals": []
    },
    {
      "num": 24,
      "timestamp": "2019-10-09T17:00:00+00:00",
      "direction": "BUY",
      "price": 8619.0,
      "qty": 0.24278,
      "btc_pct_before": 0.6036,
      "btc_pct_target": 0.8,
      "btc_pct_after": 0.8002,
      "portfolio_usdt": 10654.88,
      "signals": [
        "regime_bull"
      ]
    },
    {
      "num": 25,
      "timestamp": "2019-10-12T17:00:00+00:00",
      "direction": "SELL",
      "price": 8324.0,
      "qty": 0.24221,
      "btc_pct_before": 0.7946,
      "btc_pct_target": 0.6,
      "btc_pct_after": 0.6002,
      "portfolio_usdt": 10359.99,
      "signals": []
    },
    {
      "num": 26,
      "timestamp": "2019-10-25T17:00:00+00:00",
      "direction": "BUY",
      "price": 8496.8,
      "qty": 0.240534,
      "btc_pct_before": 0.6051,
      "btc_pct_target": 0.8,
      "btc_pct_after": 0.8002,
      "portfolio_usdt": 10486.01,
      "signals": [
        "regime_bull"
      ]
    },
    {
      "num": 27,
      "timestamp": "2019-11-15T01:00:00+00:00",
      "direction": "SELL",
      "price": 8555.0,
      "qty": 0.248044,
      "btc_pct_before": 0.8013,
      "btc_pct_target": 0.6,
      "btc_pct_after": 0.6002,
      "portfolio_usdt": 10540.4,
      "signals": []
    },
    {
      "num": 28,
      "timestamp": "2019-11-25T01:00:00+00:00",
      "direction": "SELL",
      "price": 6713.1,
      "qty": 0.192517,
      "btc_pct_before": 0.5409,
      "btc_pct_target": 0.4,
      "btc_pct_after": 0.4001,
      "portfolio_usdt": 9175.6,
      "signals": [
        "regime_bear"
      ]
    },
    {
      "num": 29,
      "timestamp": "2020-02-08T01:00:00+00:00",
      "direction": "BUY",
      "price": 9787.4,
      "qty": 0.340491,
      "btc_pct_before": 0.493,
      "btc_pct_target": 0.8,
      "btc_pct_after": 0.8004,
      "portfolio_usdt": 10854.47,
      "signals": [
        "regime_bull"
      ]
    },
    {
      "num": 30,
      "timestamp": "2020-02-26T17:00:00+00:00",
      "direction": "SELL",
      "price": 8729.8,
      "qty": 0.206025,
      "btc_pct_before": 0.7815,
      "btc_pct_target": 0.6,
      "btc_pct_after": 0.6002,
      "portfolio_usdt": 9911.15,
      "signals": []
    },
    {
      "num": 31,
      "timestamp": "2020-03-02T01:00:00+00:00",
      "direction": "SELL",
      "price": 8561.1,
      "qty": 0.223611,
      "btc_pct_before": 0.5955,
      "btc_pct_target": 0.4,
      "btc_pct_after": 0.4001,
      "portfolio_usdt": 9793.54,
      "signals": [
        "regime_bear"
      ]
    },
    {
      "num": 32,
      "timestamp": "2020-03-05T01:00:00+00:00",
      "direction": "BUY",
      "price": 8870.7,
      "qty": 0.214223,
      "btc_pct_before": 0.4087,
      "btc_pct_target": 0.6,
      "btc_pct_after": 0.6002,
      "portfolio_usdt": 9932.33,
      "signals": []
    },
    {
      "num": 33,
      "timestamp": "2020-03-09T01:00:00+00:00",
      "direction": "SELL",
      "price": 8081.7,
      "qty": 0.206586,
      "btc_pct_before": 0.5776,
      "btc_pct_target": 0.4,
      "btc_pct_after": 0.4001,
      "portfolio_usdt": 9399.43,
      "signals": [
        "regime_bear"
      ]
    },
    {
      "num": 34,
      "timestamp": "2020-03-13T01:00:00+00:00",
      "direction": "BUY",
      "price": 4119.3,
      "qty": 0.268256,
      "btc_pct_before": 0.2537,
      "btc_pct_target": 0.4,
      "btc_pct_after": 0.4001,
      "portfolio_usdt": 7553.53,
      "signals": [
        "regime_bear"
      ]
    },
    {
      "num": 35,
      "timestamp": "2020-03-19T17:00:00+00:00",
      "direction": "SELL",
      "price": 6308.7,
      "qty": 0.152834,
      "btc_pct_before": 0.5053,
      "btc_pct_target": 0.4,
      "btc_pct_after": 0.4001,
      "portfolio_usdt": 9157.75,
      "signals": [
        "regime_bear"
      ]
    },
    {
      "num": 36,
      "timestamp": "2020-05-07T13:00:00+00:00",
      "direction": "SELL",
      "price": 9484.8,
      "qty": 0.116722,
      "btc_pct_before": 0.5006,
      "btc_pct_target": 0.4,
      "btc_pct_after": 0.4001,
      "portfolio_usdt": 11000.48,
      "signals": [
        "regime_bear"
      ]
    },
    {
      "num": 37,
      "timestamp": "2020-05-11T01:00:00+00:00",
      "direction": "BUY",
      "price": 8710.0,
      "qty": 0.146835,
      "btc_pct_before": 0.3798,
      "btc_pct_target": 0.5,
      "btc_pct_after": 0.5001,
      "portfolio_usdt": 10639.38,
      "signals": [
        "regime_bear",
        "halving_post_halving"
      ]
    },
    {
      "num": 38,
      "timestamp": "2020-05-17T01:00:00+00:00",
      "direction": "BUY",
      "price": 9473.6,
      "qty": 0.444117,
      "btc_pct_before": 0.5211,
      "btc_pct_target": 0.9,
      "btc_pct_after": 0.9005,
      "portfolio_usdt": 11103.83,
      "signals": [
        "regime_bull",
        "halving_post_halving"
      ]
    },
    {
      "num": 39,
      "timestamp": "2020-09-30T01:00:00+00:00",
      "direction": "SELL",
      "price": 10789.4,
      "qty": 0.244831,
      "btc_pct_before": 0.9116,
      "btc_pct_target": 0.7,
      "btc_pct_after": 0.7002,
      "portfolio_usdt": 12485.52,
      "signals": [
        "halving_post_halving"
      ]
    },
    {
      "num": 40,
      "timestamp": "2020-10-11T01:00:00+00:00",
      "direction": "BUY",
      "price": 11366.5,
      "qty": 0.215263,
      "btc_pct_before": 0.711,
      "btc_pct_target": 0.9,
      "btc_pct_after": 0.9003,
      "portfolio_usdt": 12949.03,
      "signals": [
        "regime_bull",
        "halving_post_halving"
      ]
    },
    {
      "num": 41,
      "timestamp": "2020-11-18T01:00:00+00:00",
      "direction": "SELL",
      "price": 17650.0,
      "qty": 0.146534,
      "btc_pct_before": 0.9334,
      "btc_pct_target": 0.8,
      "btc_pct_after": 0.8002,
      "portfolio_usdt": 19387.87,
      "signals": [
        "regime_bull",
        "halving_bull_peak",
        "mvrv_2.52"
      ]
    },
    {
      "num": 42,
      "timestamp": "2020-11-27T01:00:00+00:00",
      "direction": "BUY",
      "price": 17296.4,
      "qty": 0.113685,
      "btc_pct_before": 0.7969,
      "btc_pct_target": 0.9,
      "btc_pct_after": 0.9001,
      "portfolio_usdt": 19073.25,
      "signals": [
        "regime_bull",
        "halving_bull_peak"
      ]
    },
    {
      "num": 43,
      "timestamp": "2020-12-01T01:00:00+00:00",
      "direction": "SELL",
      "price": 19602.0,
      "qty": 0.120768,
      "btc_pct_before": 0.9108,
      "btc_pct_target": 0.8,
      "btc_pct_after": 0.8001,
      "portfolio_usdt": 21358.51,
      "signals": [
        "regime_bull",
        "halving_bull_peak",
        "mvrv_2.64"
      ]
    },
    {
      "num": 44,
      "timestamp": "2020-12-05T01:00:00+00:00",
      "direction": "BUY",
      "price": 18649.1,
      "qty": 0.11881,
      "btc_pct_before": 0.792,
      "btc_pct_target": 0.9,
      "btc_pct_after": 0.9001,
      "portfolio_usdt": 20524.33,
      "signals": [
        "regime_bull",
        "halving_bull_peak"
      ]
    },
    {
      "num": 45,
      "timestamp": "2020-12-08T01:00:00+00:00",
      "direction": "SELL",
      "price": 19210.8,
      "qty": 0.112768,
      "btc_pct_before": 0.9028,
      "btc_pct_target": 0.8,
      "btc_pct_after": 0.8001,
      "portfolio_usdt": 21077.37,
      "signals": [
        "regime_bull",
        "halving_bull_peak",
        "mvrv_2.52"
      ]
    },
    {
      "num": 46,
      "timestamp": "2020-12-11T01:00:00+00:00",
      "direction": "BUY",
      "price": 17894.1,
      "qty": 0.124084,
      "btc_pct_before": 0.7885,
      "btc_pct_target": 0.9,
      "btc_pct_after": 0.9002,
      "portfolio_usdt": 19918.41,
      "signals": [
        "regime_bull",
        "halving_bull_peak"
      ]
    },
    {
      "num": 47,
      "timestamp": "2020-12-17T01:00:00+00:00",
      "direction": "SELL",
      "price": 21722.8,
      "qty": 0.12713,
      "btc_pct_before": 0.9163,
      "btc_pct_target": 0.8,
      "btc_pct_after": 0.8001,
      "portfolio_usdt": 23750.73,
      "signals": [
        "regime_bull",
        "halving_bull_peak",
        "mvrv_2.70"
      ]
    },
    {
      "num": 48,
      "timestamp": "2021-02-14T05:00:00+00:00",
      "direction": "SELL",
      "price": 48939.8,
      "qty": 0.097355,
      "btc_pct_before": 0.9002,
      "btc_pct_target": 0.8,
      "btc_pct_after": 0.8001,
      "portfolio_usdt": 47552.86,
      "signals": [
        "regime_bull",
        "halving_bull_peak",
        "mvrv_3.55"
      ]
    },
    {
      "num": 49,
      "timestamp": "2021-05-15T09:00:00+00:00",
      "direction": "BUY",
      "price": 48655.2,
      "qty": 0.098056,
      "btc_pct_before": 0.7992,
      "btc_pct_target": 0.9,
      "btc_pct_after": 0.9001,
      "portfolio_usdt": 47324.49,
      "signals": [
        "regime_bull",
        "halving_bull_peak"
      ]
    },
    {
      "num": 50,
      "timestamp": "2021-05-19T01:00:00+00:00",
      "direction": "SELL",
      "price": 40833.4,
      "qty": 0.18161,
      "btc_pct_before": 0.8832,
      "btc_pct_target": 0.7,
      "btc_pct_after": 0.7002,
      "portfolio_usdt": 40470.24,
      "signals": [
        "halving_bull_peak"
      ]
    },
    {
      "num": 51,
      "timestamp": "2021-06-23T01:00:00+00:00",
      "direction": "SELL",
      "price": 34005.4,
      "qty": 0.168534,
      "btc_pct_before": 0.6604,
      "btc_pct_target": 0.5,
      "btc_pct_after": 0.5001,
      "portfolio_usdt": 35722.03,
      "signals": [
        "regime_bear",
        "halving_bull_peak"
      ]
    },
    {
      "num": 52,
      "timestamp": "2021-08-16T01:00:00+00:00",
      "direction": "BUY",
      "price": 47638.1,
      "qty": 0.284751,
      "btc_pct_before": 0.5836,
      "btc_pct_target": 0.9,
      "btc_pct_after": 0.9004,
      "portfolio_usdt": 42873.88,
      "signals": [
        "regime_bull",
        "halving_bull_peak"
      ]
    },
    {
      "num": 53,
      "timestamp": "2021-09-07T01:00:00+00:00",
      "direction": "SELL",
      "price": 52504.3,
      "qty": 0.096982,
      "btc_pct_before": 0.9088,
      "btc_pct_target": 0.8,
      "btc_pct_after": 0.8001,
      "portfolio_usdt": 46795.11,
      "signals": [
        "regime_bull",
        "halving_bull_peak",
        "mvrv_2.52"
      ]
    },
    {
      "num": 54,
      "timestamp": "2021-09-10T01:00:00+00:00",
      "direction": "BUY",
      "price": 46902.0,
      "qty": 0.108142,
      "btc_pct_before": 0.7815,
      "btc_pct_target": 0.9,
      "btc_pct_after": 0.9002,
      "portfolio_usdt": 42792.98,
      "signals": [
        "regime_bull",
        "halving_bull_peak"
      ]
    },
    {
      "num": 55,
      "timestamp": "2021-09-21T01:00:00+00:00",
      "direction": "SELL",
      "price": 42756.2,
      "qty": 0.176409,
      "btc_pct_before": 0.8915,
      "btc_pct_target": 0.7,
      "btc_pct_after": 0.7002,
      "portfolio_usdt": 39381.04,
      "signals": [
        "halving_bull_peak"
      ]
    },
    {
      "num": 56,
      "timestamp": "2021-09-24T01:00:00+00:00",
      "direction": "BUY",
      "price": 44462.3,
      "qty": 0.174439,
      "btc_pct_before": 0.7084,
      "btc_pct_target": 0.9,
      "btc_pct_after": 0.9003,
      "portfolio_usdt": 40469.73,
      "signals": [
        "regime_bull",
        "halving_bull_peak"
      ]
    },
    {
      "num": 57,
      "timestamp": "2021-09-27T17:00:00+00:00",
      "direction": "SELL",
      "price": 43053.3,
      "qty": 0.180143,
      "btc_pct_before": 0.8973,
      "btc_pct_target": 0.7,
      "btc_pct_after": 0.7002,
      "portfolio_usdt": 39303.86,
      "signals": [
        "halving_bull_peak"
      ]
    },
    {
      "num": 58,
      "timestamp": "2021-09-30T17:00:00+00:00",
      "direction": "BUY",
      "price": 43335.5,
      "qty": 0.180734,
      "btc_pct_before": 0.7016,
      "btc_pct_target": 0.9,
      "btc_pct_after": 0.9003,
      "portfolio_usdt": 39472.57,
      "signals": [
        "regime_bull",
        "halving_bull_peak"
      ]
    },
    {
      "num": 59,
      "timestamp": "2021-10-07T01:00:00+00:00",
      "direction": "SELL",
      "price": 54796.4,
      "qty": 0.106497,
      "btc_pct_before": 0.9194,
      "btc_pct_target": 0.8,
      "btc_pct_after": 0.8001,
      "portfolio_usdt": 48856.15,
      "signals": [
        "regime_bull",
        "halving_bull_peak",
        "mvrv_2.57"
      ]
    },
    {
      "num": 60,
      "timestamp": "2021-11-02T01:00:00+00:00",
      "direction": "SELL",
      "price": 61335.1,
      "qty": 0.18981,
      "btc_pct_before": 0.8176,
      "btc_pct_target": 0.6,
      "btc_pct_after": 0.6002,
      "portfolio_usdt": 53511.3,
      "signals": [
        "regime_bull",
        "halving_bear_onset",
        "mvrv_2.64"
      ]
    },
    {
      "num": 61,
      "timestamp": "2021-11-17T01:00:00+00:00",
      "direction": "BUY",
      "price": 59320.7,
      "qty": 0.095332,
      "btc_pct_before": 0.5922,
      "btc_pct_target": 0.7,
      "btc_pct_after": 0.7001,
      "portfolio_usdt": 52439.37,
      "signals": [
        "regime_bull",
        "halving_bear_onset"
      ]
    },
    {
      "num": 62,
      "timestamp": "2021-12-04T05:00:00+00:00",
      "direction": "SELL",
      "price": 47508.3,
      "qty": 0.143918,
      "btc_pct_before": 0.6515,
      "btc_pct_target": 0.5,
      "btc_pct_after": 0.5001,
      "portfolio_usdt": 45121.39,
      "signals": [
        "halving_bear_onset"
      ]
    },
    {
      "num": 63,
      "timestamp": "2021-12-24T01:00:00+00:00",
      "direction": "BUY",
      "price": 51331.0,
      "qty": 0.165055,
      "btc_pct_before": 0.5195,
      "btc_pct_target": 0.7,
      "btc_pct_after": 0.7002,
      "portfolio_usdt": 46926.47,
      "signals": [
        "regime_bull",
        "halving_bear_onset"
      ]
    },
    {
      "num": 64,
      "timestamp": "2021-12-27T01:00:00+00:00",
      "direction": "SELL",
      "price": 50791.2,
      "qty": 0.181506,
      "btc_pct_before": 0.698,
      "btc_pct_target": 0.5,
      "btc_pct_after": 0.5001,
      "portfolio_usdt": 46568.32,
      "signals": [
        "halving_bear_onset"
      ]
    },
    {
      "num": 65,
      "timestamp": "2022-01-05T01:00:00+00:00",
      "direction": "SELL",
      "price": 46114.5,
      "qty": 0.169514,
      "btc_pct_before": 0.476,
      "btc_pct_target": 0.3,
      "btc_pct_after": 0.3001,
      "portfolio_usdt": 44410.56,
      "signals": [
        "regime_bear",
        "halving_bear_onset"
      ]
    },
    {
      "num": 66,
      "timestamp": "2022-06-13T01:00:00+00:00",
      "direction": "BUY",
      "price": 25775.2,
      "qty": 0.159452,
      "btc_pct_before": 0.1933,
      "btc_pct_target": 0.3,
      "btc_pct_after": 0.3,
      "portfolio_usdt": 38522.51,
      "signals": [
        "regime_bear",
        "halving_bear_onset"
      ]
    },
    {
      "num": 67,
      "timestamp": "2022-10-28T01:00:00+00:00",
      "direction": "BUY",
      "price": 20325.8,
      "qty": 0.261528,
      "btc_pct_before": 0.2526,
      "btc_pct_target": 0.4,
      "btc_pct_after": 0.4001,
      "portfolio_usdt": 36073.01,
      "signals": [
        "regime_bear"
      ]
    },
    {
      "num": 68,
      "timestamp": "2023-02-03T01:00:00+00:00",
      "direction": "BUY",
      "price": 23555.6,
      "qty": 0.592821,
      "btc_pct_before": 0.4359,
      "btc_pct_target": 0.8,
      "btc_pct_after": 0.8004,
      "portfolio_usdt": 38357.85,
      "signals": [
        "regime_bull"
      ]
    },
    {
      "num": 69,
      "timestamp": "2023-03-09T21:00:00+00:00",
      "direction": "SELL",
      "price": 20216.6,
      "qty": 0.294026,
      "btc_pct_before": 0.7749,
      "btc_pct_target": 0.6,
      "btc_pct_after": 0.6002,
      "portfolio_usdt": 33987.13,
      "signals": []
    },
    {
      "num": 70,
      "timestamp": "2023-03-12T21:00:00+00:00",
      "direction": "BUY",
      "price": 21274.8,
      "qty": 0.309136,
      "btc_pct_before": 0.6123,
      "btc_pct_target": 0.8,
      "btc_pct_after": 0.8002,
      "portfolio_usdt": 35045.61,
      "signals": [
        "regime_bull"
      ]
    },
    {
      "num": 71,
      "timestamp": "2023-08-04T01:00:00+00:00",
      "direction": "SELL",
      "price": 29198.8,
      "qty": 0.383304,
      "btc_pct_before": 0.8461,
      "btc_pct_target": 0.6,
      "btc_pct_after": 0.6002,
      "portfolio_usdt": 45478.19,
      "signals": []
    },
    {
      "num": 72,
      "timestamp": "2023-08-29T17:00:00+00:00",
      "direction": "BUY",
      "price": 27895.7,
      "qty": 0.334308,
      "btc_pct_before": 0.5892,
      "btc_pct_target": 0.8,
      "btc_pct_after": 0.8003,
      "portfolio_usdt": 44243.63,
      "signals": [
        "regime_bull"
      ]
    },
    {
      "num": 73,
      "timestamp": "2023-09-01T17:00:00+00:00",
      "direction": "SELL",
      "price": 25480.2,
      "qty": 0.299494,
      "btc_pct_before": 0.7854,
      "btc_pct_target": 0.6,
      "btc_pct_after": 0.6002,
      "portfolio_usdt": 41164.78,
      "signals": []
    },
    {
      "num": 74,
      "timestamp": "2023-09-14T17:00:00+00:00",
      "direction": "BUY",
      "price": 26650.9,
      "qty": 0.300058,
      "btc_pct_before": 0.6109,
      "btc_pct_target": 0.8,
      "btc_pct_after": 0.8002,
      "portfolio_usdt": 42288.14,
      "signals": [
        "regime_bull"
      ]
    },
    {
      "num": 75,
      "timestamp": "2023-09-17T17:00:00+00:00",
      "direction": "SELL",
      "price": 26477.4,
      "qty": 0.316372,
      "btc_pct_before": 0.7992,
      "btc_pct_target": 0.6,
      "btc_pct_after": 0.6002,
      "portfolio_usdt": 42055.9,
      "signals": []
    },
    {
      "num": 76,
      "timestamp": "2023-09-20T17:00:00+00:00",
      "direction": "BUY",
      "price": 27198.6,
      "qty": 0.303826,
      "btc_pct_before": 0.6066,
      "btc_pct_target": 0.8,
      "btc_pct_after": 0.8002,
      "portfolio_usdt": 42730.66,
      "signals": [
        "regime_bull"
      ]
    },
    {
      "num": 77,
      "timestamp": "2023-09-23T17:00:00+00:00",
      "direction": "SELL",
      "price": 26596.5,
      "qty": 0.625764,
      "btc_pct_before": 0.7966,
      "btc_pct_target": 0.4,
      "btc_pct_after": 0.4002,
      "portfolio_usdt": 41961.51,
      "signals": [
        "regime_bear"
      ]
    },
    {
      "num": 78,
      "timestamp": "2023-10-17T01:00:00+00:00",
      "direction": "BUY",
      "price": 28352.5,
      "qty": 0.583475,
      "btc_pct_before": 0.4157,
      "btc_pct_target": 0.8,
      "btc_pct_after": 0.8005,
      "portfolio_usdt": 43044.74,
      "signals": [
        "regime_bull"
      ]
    },
    {
      "num": 79,
      "timestamp": "2024-02-04T01:00:00+00:00",
      "direction": "SELL",
      "price": 43040.8,
      "qty": 0.366158,
      "btc_pct_before": 0.859,
      "btc_pct_target": 0.6,
      "btc_pct_after": 0.6002,
      "portfolio_usdt": 60859.72,
      "signals": []
    },
    {
      "num": 80,
      "timestamp": "2024-02-10T01:00:00+00:00",
      "direction": "BUY",
      "price": 47300.1,
      "qty": 0.241654,
      "btc_pct_before": 0.6226,
      "btc_pct_target": 0.8,
      "btc_pct_after": 0.8002,
      "portfolio_usdt": 64449.68,
      "signals": [
        "regime_bull"
      ]
    },
    {
      "num": 81,
      "timestamp": "2024-02-29T01:00:00+00:00",
      "direction": "SELL",
      "price": 61367.6,
      "qty": 0.18018,
      "btc_pct_before": 0.8386,
      "btc_pct_target": 0.7,
      "btc_pct_after": 0.7001,
      "portfolio_usdt": 79766.88,
      "signals": [
        "regime_bull",
        "mvrv_2.58"
      ]
    },
    {
      "num": 82,
      "timestamp": "2024-04-17T17:00:00+00:00",
      "direction": "BUY",
      "price": 61280.6,
      "qty": 0.130208,
      "btc_pct_before": 0.6998,
      "btc_pct_target": 0.8,
      "btc_pct_after": 0.8001,
      "portfolio_usdt": 79671.14,
      "signals": [
        "regime_bull"
      ]
    },
    {
      "num": 83,
      "timestamp": "2024-04-30T13:00:00+00:00",
      "direction": "BUY",
      "price": 60827.2,
      "qty": 0.131577,
      "btc_pct_before": 0.7989,
      "btc_pct_target": 0.9,
      "btc_pct_after": 0.9001,
      "portfolio_usdt": 79187.59,
      "signals": [
        "regime_bull",
        "halving_post_halving"
      ]
    },
    {
      "num": 84,
      "timestamp": "2024-07-04T01:00:00+00:00",
      "direction": "SELL",
      "price": 58580.1,
      "qty": 0.257016,
      "btc_pct_before": 0.8967,
      "btc_pct_target": 0.7,
      "btc_pct_after": 0.7002,
      "portfolio_usdt": 76542.75,
      "signals": [
        "halving_post_halving"
      ]
    },
    {
      "num": 85,
      "timestamp": "2024-07-10T05:00:00+00:00",
      "direction": "BUY",
      "price": 58972.1,
      "qty": 0.258636,
      "btc_pct_before": 0.7016,
      "btc_pct_target": 0.9,
      "btc_pct_after": 0.9003,
      "portfolio_usdt": 76878.71,
      "signals": [
        "regime_bull",
        "halving_post_halving"
      ]
    },
    {
      "num": 86,
      "timestamp": "2024-07-13T05:00:00+00:00",
      "direction": "SELL",
      "price": 58072.1,
      "qty": 0.259589,
      "btc_pct_before": 0.8989,
      "btc_pct_target": 0.7,
      "btc_pct_after": 0.7002,
      "portfolio_usdt": 75799.87,
      "signals": [
        "halving_post_halving"
      ]
    },
    {
      "num": 87,
      "timestamp": "2024-07-16T05:00:00+00:00",
      "direction": "BUY",
      "price": 63662.0,
      "qty": 0.229789,
      "btc_pct_before": 0.7191,
      "btc_pct_target": 0.9,
      "btc_pct_after": 0.9002,
      "portfolio_usdt": 80884.71,
      "signals": [
        "regime_bull",
        "halving_post_halving"
      ]
    },
    {
      "num": 88,
      "timestamp": "2024-08-04T17:00:00+00:00",
      "direction": "SELL",
      "price": 57871.3,
      "qty": 0.245472,
      "btc_pct_before": 0.8913,
      "btc_pct_target": 0.7,
      "btc_pct_after": 0.7002,
      "portfolio_usdt": 74241.21,
      "signals": [
        "halving_post_halving"
      ]
    },
    {
      "num": 89,
      "timestamp": "2024-08-08T21:00:00+00:00",
      "direction": "BUY",
      "price": 61168.4,
      "qty": 0.237589,
      "btc_pct_before": 0.7117,
      "btc_pct_target": 0.9,
      "btc_pct_after": 0.9003,
      "portfolio_usdt": 77180.73,
      "signals": [
        "regime_bull",
        "halving_post_halving"
      ]
    },
    {
      "num": 90,
      "timestamp": "2024-08-11T21:00:00+00:00",
      "direction": "SELL",
      "price": 59018.0,
      "qty": 0.249395,
      "btc_pct_before": 0.897,
      "btc_pct_target": 0.7,
      "btc_pct_after": 0.7002,
      "portfolio_usdt": 74716.93,
      "signals": [
        "halving_post_halving"
      ]
    },
    {
      "num": 91,
      "timestamp": "2024-08-20T01:00:00+00:00",
      "direction": "BUY",
      "price": 60444.5,
      "qty": 0.244804,
      "btc_pct_before": 0.7052,
      "btc_pct_target": 0.9,
      "btc_pct_after": 0.9003,
      "portfolio_usdt": 75959.03,
      "signals": [
        "regime_bull",
        "halving_post_halving"
      ]
    },
    {
      "num": 92,
      "timestamp": "2024-08-27T21:00:00+00:00",
      "direction": "SELL",
      "price": 60415.3,
      "qty": 0.251548,
      "btc_pct_before": 0.9002,
      "btc_pct_target": 0.7,
      "btc_pct_after": 0.7002,
      "portfolio_usdt": 75903.8,
      "signals": [
        "halving_post_halving"
      ]
    },
    {
      "num": 93,
      "timestamp": "2024-09-07T01:00:00+00:00",
      "direction": "SELL",
      "price": 53815.4,
      "qty": 0.228374,
      "btc_pct_before": 0.6754,
      "btc_pct_target": 0.5,
      "btc_pct_after": 0.5001,
      "portfolio_usdt": 70076.68,
      "signals": [
        "regime_bear",
        "halving_post_halving"
      ]
    },
    {
      "num": 94,
      "timestamp": "2024-09-22T01:00:00+00:00",
      "direction": "BUY",
      "price": 63038.0,
      "qty": 0.434874,
      "btc_pct_before": 0.5396,
      "btc_pct_target": 0.9,
      "btc_pct_after": 0.9005,
      "portfolio_usdt": 76062.94,
      "signals": [
        "regime_bull",
        "halving_post_halving"
      ]
    },
    {
      "num": 95,
      "timestamp": "2024-10-03T13:00:00+00:00",
      "direction": "SELL",
      "price": 60377.7,
      "qty": 0.238079,
      "btc_pct_before": 0.8966,
      "btc_pct_target": 0.7,
      "btc_pct_after": 0.7002,
      "portfolio_usdt": 73132.83,
      "signals": [
        "halving_post_halving"
      ]
    },
    {
      "num": 96,
      "timestamp": "2024-10-06T13:00:00+00:00",
      "direction": "BUY",
      "price": 62251.8,
      "qty": 0.232093,
      "btc_pct_before": 0.7066,
      "btc_pct_target": 0.9,
      "btc_pct_after": 0.9003,
      "portfolio_usdt": 74700.28,
      "signals": [
        "regime_bull",
        "halving_post_halving"
      ]
    },
    {
      "num": 97,
      "timestamp": "2024-10-10T17:00:00+00:00",
      "direction": "SELL",
      "price": 59604.0,
      "qty": 0.236516,
      "btc_pct_before": 0.8963,
      "btc_pct_target": 0.7,
      "btc_pct_after": 0.7002,
      "portfolio_usdt": 71819.05,
      "signals": [
        "halving_post_halving"
      ]
    },
    {
      "num": 98,
      "timestamp": "2024-10-16T01:00:00+00:00",
      "direction": "BUY",
      "price": 67374.1,
      "qty": 0.203184,
      "btc_pct_before": 0.7253,
      "btc_pct_target": 0.9,
      "btc_pct_after": 0.9002,
      "portfolio_usdt": 78351.65,
      "signals": [
        "regime_bull",
        "halving_post_halving"
      ]
    },
    {
      "num": 99,
      "timestamp": "2024-11-12T01:00:00+00:00",
      "direction": "SELL",
      "price": 88539.9,
      "qty": 0.138718,
      "btc_pct_before": 0.9222,
      "btc_pct_target": 0.8,
      "btc_pct_after": 0.8001,
      "portfolio_usdt": 100484.08,
      "signals": [
        "regime_bull",
        "halving_bull_peak",
        "mvrv_2.61"
      ]
    },
    {
      "num": 100,
      "timestamp": "2025-01-17T01:00:00+00:00",
      "direction": "SELL",
      "price": 101658.4,
      "qty": 0.134121,
      "btc_pct_before": 0.8213,
      "btc_pct_target": 0.7,
      "btc_pct_after": 0.7001,
      "portfolio_usdt": 112376.24,
      "signals": [
        "halving_bull_peak"
      ]
    },
    {
      "num": 101,
      "timestamp": "2025-01-21T01:00:00+00:00",
      "direction": "BUY",
      "price": 101492.0,
      "qty": 0.221394,
      "btc_pct_before": 0.6998,
      "btc_pct_target": 0.9,
      "btc_pct_after": 0.9003,
      "portfolio_usdt": 112227.04,
      "signals": [
        "regime_bull",
        "halving_bull_peak"
      ]
    },
    {
      "num": 102,
      "timestamp": "2025-01-24T01:00:00+00:00",
      "direction": "SELL",
      "price": 103244.6,
      "qty": 0.222696,
      "btc_pct_before": 0.9018,
      "btc_pct_target": 0.7,
      "btc_pct_after": 0.7002,
      "portfolio_usdt": 113937.5,
      "signals": [
        "halving_bull_peak"
      ]
    },
    {
      "num": 103,
      "timestamp": "2025-02-03T01:00:00+00:00",
      "direction": "BUY",
      "price": 93477.6,
      "qty": 0.251513,
      "btc_pct_before": 0.6789,
      "btc_pct_target": 0.9,
      "btc_pct_after": 0.9003,
      "portfolio_usdt": 106358.02,
      "signals": [
        "regime_bull",
        "halving_bull_peak"
      ]
    },
    {
      "num": 104,
      "timestamp": "2025-02-26T17:00:00+00:00",
      "direction": "SELL",
      "price": 86051.3,
      "qty": 0.220971,
      "btc_pct_before": 0.8926,
      "btc_pct_target": 0.7,
      "btc_pct_after": 0.7002,
      "portfolio_usdt": 98718.12,
      "signals": [
        "halving_bull_peak"
      ]
    },
    {
      "num": 105,
      "timestamp": "2025-03-01T21:00:00+00:00",
      "direction": "BUY",
      "price": 86070.9,
      "qty": 0.229071,
      "btc_pct_before": 0.7003,
      "btc_pct_target": 0.9,
      "btc_pct_after": 0.9003,
      "portfolio_usdt": 98705.35,
      "signals": [
        "regime_bull",
        "halving_bull_peak"
      ]
    },
    {
      "num": 106,
      "timestamp": "2025-03-08T01:00:00+00:00",
      "direction": "SELL",
      "price": 86099.9,
      "qty": 0.229625,
      "btc_pct_before": 0.9003,
      "btc_pct_target": 0.7,
      "btc_pct_after": 0.7002,
      "portfolio_usdt": 98705.7,
      "signals": [
        "halving_bull_peak"
      ]
    },
    {
      "num": 107,
      "timestamp": "2025-03-19T21:00:00+00:00",
      "direction": "BUY",
      "price": 85634.0,
      "qty": 0.230653,
      "btc_pct_before": 0.6991,
      "btc_pct_target": 0.9,
      "btc_pct_after": 0.9003,
      "portfolio_usdt": 98302.17,
      "signals": [
        "regime_bull",
        "halving_bull_peak"
      ]
    },
    {
      "num": 108,
      "timestamp": "2025-03-22T21:00:00+00:00",
      "direction": "SELL",
      "price": 84019.6,
      "qty": 0.228289,
      "btc_pct_before": 0.8985,
      "btc_pct_target": 0.7,
      "btc_pct_after": 0.7002,
      "portfolio_usdt": 96604.63,
      "signals": [
        "halving_bull_peak"
      ]
    },
    {
      "num": 109,
      "timestamp": "2025-03-25T21:00:00+00:00",
      "direction": "BUY",
      "price": 87753.2,
      "qty": 0.216453,
      "btc_pct_before": 0.7093,
      "btc_pct_target": 0.9,
      "btc_pct_after": 0.9003,
      "portfolio_usdt": 99580.86,
      "signals": [
        "regime_bull",
        "halving_bull_peak"
      ]
    },
    {
      "num": 110,
      "timestamp": "2025-03-28T21:00:00+00:00",
      "direction": "SELL",
      "price": 84059.4,
      "qty": 0.223702,
      "btc_pct_before": 0.8963,
      "btc_pct_target": 0.7,
      "btc_pct_after": 0.7002,
      "portfolio_usdt": 95779.87,
      "signals": [
        "halving_bull_peak"
      ]
    },
    {
      "num": 111,
      "timestamp": "2025-04-02T17:00:00+00:00",
      "direction": "BUY",
      "price": 86615.8,
      "qty": 0.218512,
      "btc_pct_before": 0.7065,
      "btc_pct_target": 0.9,
      "btc_pct_after": 0.9003,
      "portfolio_usdt": 97790.66,
      "signals": [
        "regime_bull",
        "halving_bull_peak"
      ]
    },
    {
      "num": 112,
      "timestamp": "2025-04-05T17:00:00+00:00",
      "direction": "SELL",
      "price": 82874.3,
      "qty": 0.222474,
      "btc_pct_before": 0.8962,
      "btc_pct_target": 0.7,
      "btc_pct_after": 0.7002,
      "portfolio_usdt": 93960.47,
      "signals": [
        "halving_bull_peak"
      ]
    },
    {
      "num": 113,
      "timestamp": "2025-04-12T17:00:00+00:00",
      "direction": "BUY",
      "price": 84760.0,
      "qty": 0.219649,
      "btc_pct_before": 0.7049,
      "btc_pct_target": 0.9,
      "btc_pct_after": 0.9003,
      "portfolio_usdt": 95429.39,
      "signals": [
        "regime_bull",
        "halving_bull_peak"
      ]
    },
    {
      "num": 114,
      "timestamp": "2025-04-15T17:00:00+00:00",
      "direction": "SELL",
      "price": 84482.8,
      "qty": 0.225147,
      "btc_pct_before": 0.9,
      "btc_pct_target": 0.7,
      "btc_pct_after": 0.7002,
      "portfolio_usdt": 95120.57,
      "signals": [
        "halving_bull_peak"
      ]
    },
    {
      "num": 115,
      "timestamp": "2025-04-23T01:00:00+00:00",
      "direction": "BUY",
      "price": 92647.9,
      "qty": 0.198114,
      "btc_pct_before": 0.7192,
      "btc_pct_target": 0.9,
      "btc_pct_after": 0.9002,
      "portfolio_usdt": 101527.31,
      "signals": [
        "regime_bull",
        "halving_bull_peak"
      ]
    },
    {
      "num": 116,
      "timestamp": "2025-06-19T01:00:00+00:00",
      "direction": "SELL",
      "price": 104609.9,
      "qty": 0.228123,
      "btc_pct_before": 0.9106,
      "btc_pct_target": 0.7,
      "btc_pct_after": 0.7002,
      "portfolio_usdt": 113297.36,
      "signals": [
        "halving_bull_peak"
      ]
    },
    {
      "num": 117,
      "timestamp": "2025-06-22T01:00:00+00:00",
      "direction": "BUY",
      "price": 102396.7,
      "qty": 0.222614,
      "btc_pct_before": 0.6957,
      "btc_pct_target": 0.9,
      "btc_pct_after": 0.9003,
      "portfolio_usdt": 111583.68,
      "signals": [
        "regime_bull",
        "halving_bull_peak"
      ]
    },
    {
      "num": 118,
      "timestamp": "2025-06-27T01:00:00+00:00",
      "direction": "SELL",
      "price": 107124.1,
      "qty": 0.221533,
      "btc_pct_before": 0.9043,
      "btc_pct_target": 0.7,
      "btc_pct_after": 0.7002,
      "portfolio_usdt": 116185.86,
      "signals": [
        "halving_bull_peak"
      ]
    },
    {
      "num": 119,
      "timestamp": "2025-07-11T01:00:00+00:00",
      "direction": "BUY",
      "price": 115968.5,
      "qty": 0.194308,
      "btc_pct_before": 0.7166,
      "btc_pct_target": 0.9,
      "btc_pct_after": 0.9002,
      "portfolio_usdt": 122865.06,
      "signals": [
        "regime_bull",
        "halving_bull_peak"
      ]
    },
    {
      "num": 120,
      "timestamp": "2025-09-09T01:00:00+00:00",
      "direction": "SELL",
      "price": 111370.1,
      "qty": 0.209043,
      "btc_pct_before": 0.8966,
      "btc_pct_target": 0.7,
      "btc_pct_after": 0.7002,
      "portfolio_usdt": 118446.58,
      "signals": [
        "halving_bull_peak"
      ]
    },
    {
      "num": 121,
      "timestamp": "2025-09-12T01:00:00+00:00",
      "direction": "BUY",
      "price": 115386.6,
      "qty": 0.202439,
      "btc_pct_before": 0.7076,
      "btc_pct_target": 0.9,
      "btc_pct_after": 0.9003,
      "portfolio_usdt": 121401.87,
      "signals": [
        "regime_bull",
        "halving_bull_peak"
      ]
    },
    {
      "num": 122,
      "timestamp": "2025-10-12T01:00:00+00:00",
      "direction": "SELL",
      "price": 109986.9,
      "qty": 0.207033,
      "btc_pct_before": 0.8959,
      "btc_pct_target": 0.7,
      "btc_pct_after": 0.7002,
      "portfolio_usdt": 116253.74,
      "signals": [
        "regime_bull",
        "halving_bear_onset"
      ]
    },
    {
      "num": 123,
      "timestamp": "2025-10-16T17:00:00+00:00",
      "direction": "SELL",
      "price": 108271.5,
      "qty": 0.209041,
      "btc_pct_before": 0.6969,
      "btc_pct_target": 0.5,
      "btc_pct_after": 0.5001,
      "portfolio_usdt": 114950.4,
      "signals": [
        "halving_bear_onset"
      ]
    },
    {
      "num": 124,
      "timestamp": "2025-10-19T17:00:00+00:00",
      "direction": "BUY",
      "price": 109116.1,
      "qty": 0.209242,
      "btc_pct_before": 0.5021,
      "btc_pct_target": 0.7,
      "btc_pct_after": 0.7002,
      "portfolio_usdt": 115364.81,
      "signals": [
        "regime_bull",
        "halving_bear_onset"
      ]
    },
    {
      "num": 125,
      "timestamp": "2025-10-22T17:00:00+00:00",
      "direction": "SELL",
      "price": 107780.1,
      "qty": 0.209645,
      "btc_pct_before": 0.6976,
      "btc_pct_target": 0.5,
      "btc_pct_after": 0.5001,
      "portfolio_usdt": 114341.8,
      "signals": [
        "halving_bear_onset"
      ]
    },
    {
      "num": 126,
      "timestamp": "2025-10-25T17:00:00+00:00",
      "direction": "BUY",
      "price": 111386.7,
      "qty": 0.199939,
      "btc_pct_before": 0.5084,
      "btc_pct_target": 0.7,
      "btc_pct_after": 0.7002,
      "portfolio_usdt": 116221.01,
      "signals": [
        "regime_bull",
        "halving_bear_onset"
      ]
    },
    {
      "num": 127,
      "timestamp": "2025-10-30T13:00:00+00:00",
      "direction": "SELL",
      "price": 107635.2,
      "qty": 0.203379,
      "btc_pct_before": 0.693,
      "btc_pct_target": 0.5,
      "btc_pct_after": 0.5001,
      "portfolio_usdt": 113447.57,
      "signals": [
        "halving_bear_onset"
      ]
    },
    {
      "num": 128,
      "timestamp": "2025-11-02T13:00:00+00:00",
      "direction": "BUY",
      "price": 110566.4,
      "qty": 0.200811,
      "btc_pct_before": 0.5069,
      "btc_pct_target": 0.7,
      "btc_pct_after": 0.7002,
      "portfolio_usdt": 114959.49,
      "signals": [
        "regime_bull",
        "halving_bear_onset"
      ]
    },
    {
      "num": 129,
      "timestamp": "2025-11-05T13:00:00+00:00",
      "direction": "SELL",
      "price": 102982.1,
      "qty": 0.196621,
      "btc_pct_before": 0.6851,
      "btc_pct_target": 0.5,
      "btc_pct_after": 0.5001,
      "portfolio_usdt": 109406.23,
      "signals": [
        "halving_bear_onset"
      ]
    },
    {
      "num": 130,
      "timestamp": "2025-11-17T01:00:00+00:00",
      "direction": "SELL",
      "price": 94782.4,
      "qty": 0.198786,
      "btc_pct_before": 0.4794,
      "btc_pct_target": 0.3,
      "btc_pct_after": 0.3001,
      "portfolio_usdt": 105020.26,
      "signals": [
        "regime_bear",
        "halving_bear_onset"
      ]
    }
  ]
}